ensemble_learning/EnsembleModels.py
ensemble_learning/__init__.py
ensemble_learning-0.0.1.dist-info/METADATA
ensemble_learning-0.0.1.dist-info/RECORD
ensemble_learning-0.0.1.dist-info/WHEEL
ensemble_learning-0.0.1.dist-info/top_level.txt
examples/__init__.py
examples/basic_example.py
